pyfinlib-0.0.10.dist-info/METADATA
pyfinlib-0.0.10.dist-info/WHEEL
pyfinlib/__init__.py
pyfinlib/pyfinlib.abi3.so
pyfinlib-0.0.10.dist-info/RECORD
