Metadata-Version: 2.4
Name: pyfinlib
Version: 0.0.10
Summary: Quant finance functions implemented in Rust
Home-Page: https://github.com/sarsoo/finlib
Author: sarsoo <andy@sarsoo.xyz>
Author-email: sarsoo <andy@sarsoo.xyz>
License: MIT
Project-URL: Source Code, https://github.com/sarsoo/finlib
